{
    "fields":[    {
              "key": "key1",
              "type": "text",
              "label": "titulo1 compare"
              },
              {
              "key": "key2",
              "type": "text",
              "label": "titulo2 compare",
              "validator": [
                            {
                            "type": "compare",
                            "textError": "texto error compare",
                            "itemsCompare": [
                                             "key1",
                                             "key2"
                                             ]
                            }
                            ]
              },
              {
              "key": "swefdsdfsadf",
              "type": "text",
              "label": "validador con 2 casos - email y mandatory",
              "placeHolder": "sdfs",
              "keyboard": "FormKeyboardTypeEmail",
              "validator": [
                            {
                                "type": "email",
                                "textError": "texto error email"
                            },
                            {
                                "type": "mandatory",
                                "textError": "texto error mandatory"
                            }
                        ],
              },
              {
              "key": "minAgetextfiled",
              "type": "datePicker",
              "label": "validador pro edad",
              "validator": [
                            {
                            "type": "age",
                            "textError": "texto error age",
                            "minAge": 12
                            },
                            {
                            "type": "mandatory",
                            "textError": "texto error mandatory"
                            }
                            ]
              },
              {
              "key": "textsize",
              "type": "text",
              "label": "texto tamaño",
              "placeHolder": "tamaño",
              "validator": [
                            {
                            "type": "lengthText",
                            "textError": "error texto tamaño",
                            "minLength": 2,
                            "maxLength": 10
                            },
                            {
                            "type": "mandatory",
                            "textError": "texto error mandatory"
                            }
                            ],
              },
              {
              "key": "keyHiddenText",
              "type": "text",
              "label": "titulo hiddden text",
              "isHidden": true
              },
              {
              "key": "keyHiddenText2",
              "type": "text",
              "label": " hiddden text titulo2",
              "isHidden": true
              },
              {
              "key": "keydatePicker",
              "type": "datePicker",
              "label": "tituloDatePicker t",
              "textError": "error_generic_field",
              "rules": {
                    "fieldReciver": ["keyHiddenText", "keyHiddenText2"],
                    "compare": ">",
                    "value": "16",
                    "behavior": "show",
                    "else": "hide"
                }              
              },{
              "key": "keyText2",
              "type": "text",
              "label": "titulo text2"
              },
              {
              "key": "dfgfd",
              "type": "index",
              "label": "sgdsgfdsg  sfsd sdsgdsgfdsg  sfsd sdsgdsgfdsg  sfsd sdsgdsgfdsg  sfsd sdsgdsgfdsg  sfsd sdsgdsgfdsg  sfsd sdsgdsgfdsg  sfsd sdsgdsgfdsg  sfsd sdsgdsgfdsg  sfsd sdsgdsgfdsg  sfsd sdsgdsgfdsg  sfsd sdsgdsgfdsg  sfsd sdsgdsgfdsg  sfsd sdsgdsgfdsg  sfsd sdsgdsgfdsg  sfsd sdsgdsgfdsg  sfsd sd"
              }
              ]
}
